.gitignore
README.rst
remote_traits.py
setup.py
stdeb.cfg
wx_demo.py
remote_traits.egg-info/PKG-INFO
remote_traits.egg-info/SOURCES.txt
remote_traits.egg-info/dependency_links.txt
remote_traits.egg-info/top_level.txt
remote_traits.egg_info/stdeb.cfg