Metadata-Version: 1.0
Name: remote-traits
Version: 0.1
Summary: use traits remotely
Home-page: http://github.com/astraw/remote_traits
Author: Andrew Straw
Author-email: strawman@astraw.com
License: MIT
Platform: UNKNOWN
